LICENSE
README.md
setup.py
anynet/__init__.py
anynet/http.py
anynet/queue.py
anynet/scheduler.py
anynet/streams.py
anynet/tcp.py
anynet/tls.py
anynet/udp.py
anynet/util.py
anynet/websocket.py
anynet/xml.py
anynet.egg-info/PKG-INFO
anynet.egg-info/SOURCES.txt
anynet.egg-info/dependency_links.txt
anynet.egg-info/requires.txt
anynet.egg-info/top_level.txt
tests/test_http.py
tests/test_queue.py
tests/test_streams.py
tests/test_tcp.py
tests/test_tls.py
tests/test_udp.py
tests/test_util.py
tests/test_websocket.py
tests/test_xml.py