Metadata-Version: 2.1
Name: anynet
Version: 1.2.0
Summary: Networking library based on anyio
Home-page: https://github.com/kinnay/anynet
Author: Yannik Marchand
Author-email: ymarchand@me.com
License: MIT
License-File: LICENSE
